MANIFEST.in
keycat-small.png
keycat.desktop
keycat.png
setup.py
KeyCat.egg-info/PKG-INFO
KeyCat.egg-info/SOURCES.txt
KeyCat.egg-info/dependency_links.txt
KeyCat.egg-info/entry_points.txt
KeyCat.egg-info/requires.txt
KeyCat.egg-info/top_level.txt
keycat/__init__.py
keycat/__main__.py
keycat/button_matcher.py
keycat/database.py
keycat/dependencies.py
keycat/desktop_entry.py
keycat/events.py
keycat/key_codes.py
keycat/keyboard_events.py
keycat/models.py
keycat/mouse_events.py
keycat/notify.py
keycat/picture_util.py
keycat/program_identifier.py
keycat/repository.py
keycat/screen.py
keycat/statistic.py
keycat/template_matcher.py
keycat/data/__init__.py
keycat/data/buttons_config.json
keycat/data/buttons/__init__.py
keycat/data/buttons/chrome/__init__.py
keycat/data/buttons/chrome/back_button.png
keycat/data/buttons/chrome/back_text.png
keycat/data/buttons/chrome/book_manager.png
keycat/data/buttons/chrome/book_open.png
keycat/data/buttons/chrome/bookmark.png
keycat/data/buttons/chrome/bookmark_button.png
keycat/data/buttons/chrome/bookmark_tabs.png
keycat/data/buttons/chrome/clear_browsing.png
keycat/data/buttons/chrome/close.png
keycat/data/buttons/chrome/close_tab.png
keycat/data/buttons/chrome/copy.png
keycat/data/buttons/chrome/cut.png
keycat/data/buttons/chrome/dev_tools.png
keycat/data/buttons/chrome/downloads.png
keycat/data/buttons/chrome/exit.png
keycat/data/buttons/chrome/find.png
keycat/data/buttons/chrome/forward_button.png
keycat/data/buttons/chrome/forward_text.png
keycat/data/buttons/chrome/history.png
keycat/data/buttons/chrome/inspect.png
keycat/data/buttons/chrome/new_incognito.png
keycat/data/buttons/chrome/new_tab.png
keycat/data/buttons/chrome/new_tab_3.png
keycat/data/buttons/chrome/new_tab_button.png
keycat/data/buttons/chrome/new_tab_template_chrome.png
keycat/data/buttons/chrome/new_windows_template_chrome.png
keycat/data/buttons/chrome/paste.png
keycat/data/buttons/chrome/paste_2.png
keycat/data/buttons/chrome/print.png
keycat/data/buttons/chrome/print_2.png
keycat/data/buttons/chrome/print_3.png
keycat/data/buttons/chrome/reload.png
keycat/data/buttons/chrome/reload_button.png
keycat/data/buttons/chrome/reload_text.png
