Metadata-Version: 1.1
Name: KeyCat
Version: 0.2.5
Summary: KeyCat
Home-page: https://github.com/KatreMetsvahi/KeyCat
Author: UNKNOWN
Author-email: UNKNOWN
License: UNKNOWN
Download-URL: https://github.com/KatreMetsvahi/KeyCat/tarball/0.2.5
Platform: UNKNOWN
